UnimiLibrary/__init__.py
UnimiLibrary/__main__.py
UnimiLibrary/config.json
UnimiLibrary/easystaff.py
UnimiLibrary/exceptions.py
unimi_library_cli-1.1.1.dist-info/METADATA
unimi_library_cli-1.1.1.dist-info/WHEEL
unimi_library_cli-1.1.1.dist-info/licenses/LICENSE
unimi_library_cli-1.1.1.dist-info/RECORD
