Metadata-Version: 2.3
Name: Unimi-Library-CLI
Version: 1.1.1
Summary: Simple CLI script to reserve spot at University of Milan (UNIMI) Library
Author: Albertobilack
License-File: LICENSE
Classifier: License :: OSI Approved :: MIT License
Classifier: Programming Language :: Python :: 3
Requires-Python: >=3.12
Requires-Dist: beautifulsoup4>=4.12.3
Requires-Dist: lxml>=5.1.0
Requires-Dist: pytz>=2024.1
Requires-Dist: requests>=2.32.3
